que_es/__init__.py
que_es/esto.py
que_es-1.0.0.dist-info/WHEEL
que_es-1.0.0.dist-info/METADATA
que_es-1.0.0.dist-info/RECORD
