Metadata-Version: 1.2
Name: que_es
Version: 1.0.0
Summary: Insanely simple module to aid in object inspection. Just import que es, then enter 'que_es.esto(obj)' to information about the objects attribute, type,
Home-page: http://github.com/N2ITN/que_es
License: UNKNOWN
Author: N2ITN
Author-email: z@aracel.io
Classifier: License :: OSI Approved :: MIT License
